[
{
    "domain": ".journaldesfemmes.fr",
    "expirationDate": 1683484711,
    "hostOnly": false,
    "httpOnly": false,
    "name": "_ga",
    "path": "/",
    "sameSite": "unspecified",
    "secure": false,
    "session": false,
    "storeId": "1",
    "value": "GA1.2.559382662.1620412712",
    "id": 1
},
{
    "domain": ".journaldesfemmes.fr",
    "expirationDate": 1620412771,
    "hostOnly": false,
    "httpOnly": false,
    "name": "_gat",
    "path": "/",
    "sameSite": "unspecified",
    "secure": false,
    "session": false,
    "storeId": "1",
    "value": "1",
    "id": 2
},
{
    "domain": ".journaldesfemmes.fr",
    "expirationDate": 1620499111,
    "hostOnly": false,
    "httpOnly": false,
    "name": "_gid",
    "path": "/",
    "sameSite": "unspecified",
    "secure": false,
    "session": false,
    "storeId": "1",
    "value": "GA1.2.918478368.1620412712",
    "id": 3
},
{
    "domain": ".sante.journaldesfemmes.fr",
    "expirationDate": 1683484711,
    "hostOnly": false,
    "httpOnly": false,
    "name": "_ga.group",
    "path": "/",
    "sameSite": "unspecified",
    "secure": false,
    "session": false,
    "storeId": "1",
    "value": "GA1.3.559382662.1620412712",
    "id": 4
},
{
    "domain": ".sante.journaldesfemmes.fr",
    "expirationDate": 1620499111,
    "hostOnly": false,
    "httpOnly": false,
    "name": "_ga.group_gid",
    "path": "/",
    "sameSite": "unspecified",
    "secure": false,
    "session": false,
    "storeId": "1",
    "value": "GA1.3.132066803.1620412712",
    "id": 5
},
{
    "domain": ".sante.journaldesfemmes.fr",
    "expirationDate": 1620412771,
    "hostOnly": false,
    "httpOnly": false,
    "name": "_gat_groupTracker",
    "path": "/",
    "sameSite": "unspecified",
    "secure": false,
    "session": false,
    "storeId": "1",
    "value": "1",
    "id": 6
},
{
    "domain": "sante.journaldesfemmes.fr",
    "hostOnly": true,
    "httpOnly": false,
    "name": "zbot0",
    "path": "/fiches-maladies/2700095-pass-sanitaire-covid-certificat-europe-france-definition-comment-l-avoir-voyage-obligatoire",
    "sameSite": "unspecified",
    "secure": false,
    "session": true,
    "storeId": "1",
    "value": "1620412711767",
    "id": 7
}
]